gensvm/__init__.py
gensvm/__version__.py
gensvm/core.py
gensvm/gridsearch.py
gensvm/sklearn_util.py
gensvm/util.py
gensvm/cython_wrapper/wrapper.cpython-37m-darwin.so
gensvm-0.2.7.dist-info/LICENSE
gensvm-0.2.7.dist-info/METADATA
gensvm-0.2.7.dist-info/WHEEL
gensvm-0.2.7.dist-info/top_level.txt
gensvm-0.2.7.dist-info/RECORD
